jupytertteditor/__init__.py
jupytertteditor/main.py
jupytertteditor-0.1.0.dist-info/METADATA
jupytertteditor-0.1.0.dist-info/WHEEL
jupytertteditor-0.1.0.dist-info/top_level.txt
jupytertteditor-0.1.0.dist-info/RECORD
