Metadata-Version: 2.4
Name: jupytertteditor
Version: 0.1.0
Summary: A tool for creating and editing Truth Tables with JuPyter Functionality
Author-email: Jacob Hutchens <jacob.hutchens.118@gmail.com>
Project-URL: Homepage, https://github.com/JacobHutchens/JuPyter-TT-Editor
Classifier: Programming Language :: Python :: 3
Classifier: License :: OSI Approved :: MIT License
Classifier: Operating System :: OS Independent
Requires-Python: >=3.7
